RomasterBot/__init__.py
RomasterBot/api_try.py
romasterbot-0.1.0.dist-info/METADATA
romasterbot-0.1.0.dist-info/WHEEL
romasterbot-0.1.0.dist-info/top_level.txt
romasterbot-0.1.0.dist-info/RECORD
