Metadata-Version: 2.4
Name: romasterbot
Version: 0.1.0
Summary: Web messenger bot API library
Author: Mitay
Requires-Python: >=3.8
Dynamic: author
Dynamic: description
Dynamic: description-content-type
Dynamic: requires-python
Dynamic: summary
